tetris/.env.dev
tetris/.env.prod
tetris/__init__.py
tetris/__main__.py
tetris/version.py
tetris/yolov8s.pt
tetris/logs/rexhttp.log
tetris/trender/__init__.py
tetris/trender/config.py
tetris/trender/minio.py
tetris/trender/models.py
tetris/trender/reddit.py
zf_tetris-2.2.0.data/data/tetris/.env.dev
zf_tetris-2.2.0.dist-info/LICENSE
zf_tetris-2.2.0.dist-info/METADATA
zf_tetris-2.2.0.dist-info/WHEEL
zf_tetris-2.2.0.dist-info/entry_points.txt
zf_tetris-2.2.0.dist-info/top_level.txt
zf_tetris-2.2.0.dist-info/RECORD
